nn_sdk/__init__.py
nn_sdk/csdk_wraper.py
nn_sdk/engine_csdk.so
nn_sdk/fasttext_inf.so
nn_sdk/nn_sdk.h
nn_sdk/nn_sdk.java
nn_sdk/test.c
nn_sdk/test_aes.py
nn_sdk/test_py.py
nn_sdk/version_config.py
nn_sdk-1.8.26.dist-info/METADATA
nn_sdk-1.8.26.dist-info/WHEEL
nn_sdk-1.8.26.dist-info/top_level.txt
nn_sdk-1.8.26.dist-info/RECORD
